{
  "name": "appUser",
  "base": "User",
  "idInjection": true,
  "options": {
    "validateUpsert": true
  },
  "properties": {
    "firstName": {
      "type": "string",
      "required": true
    },
    "lastName": {
      "type": "string",
      "required": true
    },
    "email": {
      "type": "string",
      "required": true
    }
  },
  "validations": [],
  "relations": {
    "watchlists": {
      "type": "hasMany",
      "model": "watchlist",
      "foreignKey": "userId"
    }
  },
  "acls": [
    {
      "accessType": "*",
      "principalType": "ROLE",
      "principalId": "$authenticated",
      "permission": "ALLOW"
    }
  ],
  "methods": {}
}
